uwsgidecoratorsfallback.py
uwsgidecorators_fallback-0.0.5.dist-info/LICENSE
uwsgidecorators_fallback-0.0.5.dist-info/METADATA
uwsgidecorators_fallback-0.0.5.dist-info/WHEEL
uwsgidecorators_fallback-0.0.5.dist-info/top_level.txt
uwsgidecorators_fallback-0.0.5.dist-info/RECORD
