Metadata-Version: 2.1
Name: uwsgidecorators-fallback
Version: 0.0.5
Summary: uWSGI API - Python decorators - with fallback for running outside uwsgi
Home-page: https://github.com/devopsconsulting/uwsgidecorators-fallback
Author: Lars van de Kerkhof
Author-email: lars@permanentmarkers.nl
License: GPL
Keywords: uwsgi
Platform: UNKNOWN
Requires-Dist: setuptools
Requires-Dist: uwsgidecorators
